MANIFEST.in
README.md
setup.py
bin/cmu-course-api
bin/cmu-fce-api
cmu_course_api/__init__.py
cmu_course_api/aggregate.py
cmu_course_api/parse_descs.py
cmu_course_api/parse_fces.py
cmu_course_api/parse_schedules.py
cmu_course_api.egg-info/PKG-INFO
cmu_course_api.egg-info/SOURCES.txt
cmu_course_api.egg-info/dependency_links.txt
cmu_course_api.egg-info/requires.txt
cmu_course_api.egg-info/top_level.txt