Metadata-Version: 1.0
Name: cmu-course-api
Version: 1.5.2
Summary: Python utility for retrieving information about courses at Carnegie Mellon University.
Home-page: http://scottylabs.org/course-api
Author: ScottyLabs
Author-email: info@scottylabs.org
License: MIT
Platform: UNKNOWN
